netunicorn/director/infrastructure/connectors/__init__.py
netunicorn/director/infrastructure/connectors/aci.py
netunicorn_connector_aci-0.1.5.dist-info/LICENSE
netunicorn_connector_aci-0.1.5.dist-info/METADATA
netunicorn_connector_aci-0.1.5.dist-info/WHEEL
netunicorn_connector_aci-0.1.5.dist-info/top_level.txt
netunicorn_connector_aci-0.1.5.dist-info/RECORD
