Metadata-Version: 2.1
Name: netunicorn-connector-aci
Version: 0.1.5
Summary: Azure Container Instances connector for netunicorn
Author-email: Roman Beltiukov <rbeltiukov@ucsb.edu>
License: MIT
Keywords: netunicorn
Classifier: Programming Language :: Python :: 3
Requires-Python: >=3.10
License-File: LICENSE
Requires-Dist: netunicorn-base <0.5.0,>=0.4.0
Requires-Dist: pyyaml
Requires-Dist: returns
Requires-Dist: azure-mgmt-resource
Requires-Dist: azure-mgmt-containerinstance
Requires-Dist: azure-identity
